{
	"name": "TeamsSink",
	"properties": {
		"linkedServiceName": {
			"referenceName": "AzureDataLakeStorage1",
			"type": "LinkedServiceReference"
		},
		"annotations": [],
		"type": "DelimitedText",
		"typeProperties": {
			"location": {
				"type": "AzureBlobFSLocation",
				"fileName": "Teams.csv",
				"folderPath": "raw_data",
				"fileSystem": "tokyoolympicfile"
			},
			"columnDelimiter": ",",
			"escapeChar": "\\",
			"firstRowAsHeader": true,
			"quoteChar": "\""
		},
		"schema": [
			{
				"name": "PersonName",
				"type": "String"
			},
			{
				"name": "Country",
				"type": "String"
			},
			{
				"name": "Discipline",
				"type": "String"
			}
		]
	}
}